inline_actions/__init__.py
inline_actions/actions.py
inline_actions/admin.py
inline_actions/static/inline_actions/css/inline_actions.css
inline_actions/templatetags/__init__.py
inline_actions/templatetags/inline_action_tags.py
django_admin_inlines-1.1.0.dist-info/LICENSE
django_admin_inlines-1.1.0.dist-info/METADATA
django_admin_inlines-1.1.0.dist-info/WHEEL
django_admin_inlines-1.1.0.dist-info/RECORD
