Metadata-Version: 2.3
Name: django-admin-inlines
Version: 1.1.0
Summary: django-admin-inlines adds actions to each row of the ModelAdmin or InlineModelAdmin. (A fork of django-inline-actions)
License: BSD-3-Clause
Author: Karlo Krakan
Author-email: karlo.krakan@panevo.com
Requires-Python: >=3.9,<3.14
Classifier: Development Status :: 5 - Production/Stable
Classifier: Environment :: Console
Classifier: Framework :: Django :: 3.2
Classifier: Framework :: Django :: 4.0
Classifier: Framework :: Django :: 4.1
Classifier: Framework :: Django :: 4.2
Classifier: Framework :: Django :: 5.0
Classifier: Framework :: Django :: 5.1
Classifier: Framework :: Django :: 5.2
Classifier: Intended Audience :: Developers
Classifier: License :: OSI Approved :: BSD License
Classifier: Natural Language :: English
Classifier: Operating System :: OS Independent
Classifier: Programming Language :: Python :: 3
Classifier: Programming Language :: Python :: 3.9
Classifier: Programming Language :: Python :: 3.10
Classifier: Programming Language :: Python :: 3.11
Classifier: Programming Language :: Python :: 3.12
Classifier: Programming Language :: Python :: 3.13
Classifier: Topic :: Internet
Requires-Dist: django (>=3.2,<5.3)
Project-URL: Documentation, https://github.com/Panevo/django-admin-inlines/blob/master/README.md
Project-URL: Homepage, https://github.com/Panevo/django-admin-inlines
Project-URL: Repository, https://github.com/Panevo/django-admin-inlines
